README.rst
setup.py
pytouch/__init__.py
pytouch/__main__.py
pytouch/helpers.py
pytouch/pytouch.py
pytouch_cli.egg-info/PKG-INFO
pytouch_cli.egg-info/SOURCES.txt
pytouch_cli.egg-info/dependency_links.txt
pytouch_cli.egg-info/entry_points.txt
pytouch_cli.egg-info/top_level.txt