Metadata-Version: 1.0
Name: pytouch-cli
Version: 0.1.0
Summary: A Python tool similar to UNIX's touch.
Home-page: https://github.com/cedricouellet/pytouch.git
Author: cedricao
Author-email: cedricao.noreply@gmail.com
License: UNKNOWN
Platform: UNKNOWN
